cloud_unzip/__init__.py
cloud_unzip/core.py
cloud_unzip-0.1.4.dist-info/licenses/LICENSE
cloud_unzip-0.1.4.dist-info/METADATA
cloud_unzip-0.1.4.dist-info/WHEEL
cloud_unzip-0.1.4.dist-info/entry_points.txt
cloud_unzip-0.1.4.dist-info/top_level.txt
cloud_unzip-0.1.4.dist-info/RECORD
