Metadata-Version: 2.4
Name: cloud_unzip
Version: 0.1.4
Summary: python script to extract files from remote ZIP archives without downloading the entire archive
Home-page: https://github.com/rhythmcache/cloud_unzip
Author: rhythmcache
Classifier: Programming Language :: Python :: 3
Classifier: License :: OSI Approved :: MIT License
Classifier: Operating System :: OS Independent
Requires-Python: >=3.7
License-File: LICENSE
Requires-Dist: fsspec
Requires-Dist: aiohttp
Requires-Dist: requests
Dynamic: author
Dynamic: classifier
Dynamic: description
Dynamic: description-content-type
Dynamic: home-page
Dynamic: license-file
Dynamic: requires-dist
Dynamic: requires-python
Dynamic: summary
